{
  "First Round": {
    "bin_center": [
      0.0,
      1.0,
      2.0,
      3.0,
      4.0,
      5.0,
      6.0,
      7.0,
      8.0,
      9.0,
      10.0,
      11.0,
      12.0,
      13.0,
      14.0,
      15.0,
      16.0,
      17.0,
      18.0,
      19.0,
      20.0,
      21.0,
      22.0,
      23.0,
      24.0,
      25.0,
      26.0,
      27.0,
      28.0,
      29.0,
      30.0,
      31.0,
      32.0
    ],
    "bin_start": [
      -0.5,
      0.5,
      1.5,
      2.5,
      3.5,
      4.5,
      5.5,
      6.5,
      7.5,
      8.5,
      9.5,
      10.5,
      11.5,
      12.5,
      13.5,
      14.5,
      15.5,
      16.5,
      17.5,
      18.5,
      19.5,
      20.5,
      21.5,
      22.5,
      23.5,
      24.5,
      25.5,
      26.5,
      27.5,
      28.5,
      29.5,
      30.5,
      31.5
    ],
    "bin_end": [
      0.5,
      1.5,
      2.5,
      3.5,
      4.5,
      5.5,
      6.5,
      7.5,
      8.5,
      9.5,
      10.5,
      11.5,
      12.5,
      13.5,
      14.5,
      15.5,
      16.5,
      17.5,
      18.5,
      19.5,
      20.5,
      21.5,
      22.5,
      23.5,
      24.5,
      25.5,
      26.5,
      27.5,
      28.5,
      29.5,
      30.5,
      31.5,
      32.5
    ],
    "winners_density": [
      0.0,
      0.015037593984962405,
      0.007518796992481203,
      0.03759398496240601,
      0.05263157894736842,
      0.09774436090225563,
      0.11278195488721804,
      0.14285714285714285,
      0.12781954887218044,
      0.15789473684210525,
      0.09774436090225563,
      0.07518796992481203,
      0.03759398496240601,
      0.015037593984962405,
      0.015037593984962405,
      0.007518796992481203,
      0.0,
      0.0,
      0.0,
      0.0,
      0.0,
      0.0,
      0.0,
      0.0,
      0.0,
      0.0,
      0.0,
      0.0,
      0.0,
      0.0,
      0.0,
      0.0,
      0.0
    ],
    "non_winners_density": [
      0.005080268238162975,
      0.0122942491363544,
      0.020625889046941678,
      0.03149766307661044,
      0.05222515748831538,
      0.07132696606380817,
      0.09479780532412112,
      0.1058727900833164,
      0.11105466368624263,
      0.11328998171103434,
      0.10323105059947166,
      0.0833163991058728,
      0.06563706563706563,
      0.049685023369233895,
      0.0331233489128226,
      0.01839057102214997,
      0.013818329607803293,
      0.007112375533428165,
      0.004572241414346677,
      0.0017272912009754116,
      0.0005080268238162975,
      0.0007112375533428165,
      0.0001016053647632595,
      0.0,
      0.0,
      0.0,
      0.0,
      0.0,
      0.0,
      0.0,
      0.0,
      0.0,
      0.0
    ],
    "winners_count": [
      0,
      2,
      1,
      5,
      7,
      13,
      15,
      19,
      17,
      21,
      13,
      10,
      5,
      2,
      2,
      1,
      0,
      0,
      0,
      0,
      0,
      0,
      0,
      0,
      0,
      0,
      0,
      0,
      0,
      0,
      0,
      0,
      0
    ],
    "non_winners_count": [
      50,
      121,
      203,
      310,
      514,
      702,
      933,
      1042,
      1093,
      1115,
      1016,
      820,
      646,
      489,
      326,
      181,
      136,
      70,
      45,
      17,
      5,
      7,
      1,
      0,
      0,
      0,
      0,
      0,
      0,
      0,
      0,
      0,
      0
    ],
    "winners_mean": 7.7368421052631575,
    "non_winners_mean": 8.537898801056695
  },
  "Second Round": {
    "bin_center": [
      0.0,
      1.0,
      2.0,
      3.0,
      4.0,
      5.0,
      6.0,
      7.0,
      8.0,
      9.0,
      10.0,
      11.0,
      12.0,
      13.0,
      14.0,
      15.0,
      16.0
    ],
    "bin_start": [
      -0.5,
      0.5,
      1.5,
      2.5,
      3.5,
      4.5,
      5.5,
      6.5,
      7.5,
      8.5,
      9.5,
      10.5,
      11.5,
      12.5,
      13.5,
      14.5,
      15.5
    ],
    "bin_end": [
      0.5,
      1.5,
      2.5,
      3.5,
      4.5,
      5.5,
      6.5,
      7.5,
      8.5,
      9.5,
      10.5,
      11.5,
      12.5,
      13.5,
      14.5,
      15.5,
      16.5
    ],
    "winners_density": [
      0.0,
      0.015037593984962405,
      0.045112781954887216,
      0.07518796992481203,
      0.11278195488721804,
      0.14285714285714285,
      0.24812030075187969,
      0.15037593984962405,
      0.14285714285714285,
      0.03759398496240601,
      0.022556390977443608,
      0.007518796992481203,
      0.0,
      0.0,
      0.0,
      0.0,
      0.0
    ],
    "non_winners_density": [
      0.007620402357244462,
      0.01839057102214997,
      0.035663483031904086,
      0.06025198130461289,
      0.09743954480796586,
      0.13188376346271083,
      0.14712456817719977,
      0.1415362731152205,
      0.12406015037593984,
      0.09743954480796586,
      0.06563706563706563,
      0.039626092257671205,
      0.019203413940256046,
      0.009754115017272911,
      0.003048160942897785,
      0.0013208697419223735,
      0.0
    ],
    "winners_count": [
      0,
      2,
      6,
      10,
      15,
      19,
      33,
      20,
      19,
      5,
      3,
      1,
      0,
      0,
      0,
      0,
      0
    ],
    "non_winners_count": [
      75,
      181,
      351,
      593,
      959,
      1298,
      1448,
      1393,
      1221,
      959,
      646,
      390,
      189,
      96,
      30,
      13,
      0
    ],
    "winners_mean": 5.827067669172933,
    "non_winners_mean": 6.574578337736233
  },
  "Sweet 16": {
    "bin_center": [
      0.0,
      1.0,
      2.0,
      3.0,
      4.0,
      5.0,
      6.0,
      7.0,
      8.0
    ],
    "bin_start": [
      -0.5,
      0.5,
      1.5,
      2.5,
      3.5,
      4.5,
      5.5,
      6.5,
      7.5
    ],
    "bin_end": [
      0.5,
      1.5,
      2.5,
      3.5,
      4.5,
      5.5,
      6.5,
      7.5,
      8.5
    ],
    "winners_density": [
      0.015037593984962405,
      0.03007518796992481,
      0.14285714285714285,
      0.16541353383458646,
      0.3007518796992481,
      0.20300751879699247,
      0.12781954887218044,
      0.0,
      0.015037593984962405
    ],
    "non_winners_density": [
      0.013615118878276773,
      0.03881324933956513,
      0.09327372485267223,
      0.1565738671001829,
      0.2225157488315383,
      0.21459053038000406,
      0.16084129242023978,
      0.07813452550294656,
      0.021641942694574274
    ],
    "winners_count": [
      2,
      4,
      19,
      22,
      40,
      27,
      17,
      0,
      2
    ],
    "non_winners_count": [
      134,
      382,
      918,
      1541,
      2190,
      2112,
      1583,
      769,
      213
    ],
    "winners_mean": 3.917293233082707,
    "non_winners_mean": 4.34322292217029
  },
  "Elite 8": {
    "bin_center": [
      0.0,
      1.0,
      2.0,
      3.0,
      4.0
    ],
    "bin_start": [
      -0.5,
      0.5,
      1.5,
      2.5,
      3.5
    ],
    "bin_end": [
      0.5,
      1.5,
      2.5,
      3.5,
      4.5
    ],
    "winners_density": [
      0.05263157894736842,
      0.2781954887218045,
      0.2706766917293233,
      0.3157894736842105,
      0.08270676691729323
    ],
    "non_winners_density": [
      0.04684007315586263,
      0.1678520625889047,
      0.2923186344238976,
      0.31650071123755336,
      0.17648851859378176
    ],
    "winners_count": [
      7,
      37,
      36,
      42,
      11
    ],
    "non_winners_count": [
      461,
      1652,
      2877,
      3115,
      1737
    ],
    "winners_mean": 2.0977443609022557,
    "non_winners_mean": 2.407945539524487
  },
  "Total Upsets": {
    "bin_center": [
      0.0,
      1.0,
      2.0,
      3.0,
      4.0,
      5.0,
      6.0,
      7.0,
      8.0,
      9.0,
      10.0,
      11.0,
      12.0,
      13.0,
      14.0,
      15.0,
      16.0,
      17.0,
      18.0,
      19.0,
      20.0,
      21.0,
      22.0,
      23.0,
      24.0,
      25.0,
      26.0,
      27.0,
      28.0,
      29.0,
      30.0,
      31.0,
      32.0,
      33.0,
      34.0,
      35.0,
      36.0,
      37.0,
      38.0,
      39.0,
      40.0,
      41.0,
      42.0,
      43.0,
      44.0,
      45.0,
      46.0,
      47.0,
      48.0,
      49.0,
      50.0,
      51.0
    ],
    "bin_start": [
      -0.5,
      0.5,
      1.5,
      2.5,
      3.5,
      4.5,
      5.5,
      6.5,
      7.5,
      8.5,
      9.5,
      10.5,
      11.5,
      12.5,
      13.5,
      14.5,
      15.5,
      16.5,
      17.5,
      18.5,
      19.5,
      20.5,
      21.5,
      22.5,
      23.5,
      24.5,
      25.5,
      26.5,
      27.5,
      28.5,
      29.5,
      30.5,
      31.5,
      32.5,
      33.5,
      34.5,
      35.5,
      36.5,
      37.5,
      38.5,
      39.5,
      40.5,
      41.5,
      42.5,
      43.5,
      44.5,
      45.5,
      46.5,
      47.5,
      48.5,
      49.5,
      50.5
    ],
    "bin_end": [
      0.5,
      1.5,
      2.5,
      3.5,
      4.5,
      5.5,
      6.5,
      7.5,
      8.5,
      9.5,
      10.5,
      11.5,
      12.5,
      13.5,
      14.5,
      15.5,
      16.5,
      17.5,
      18.5,
      19.5,
      20.5,
      21.5,
      22.5,
      23.5,
      24.5,
      25.5,
      26.5,
      27.5,
      28.5,
      29.5,
      30.5,
      31.5,
      32.5,
      33.5,
      34.5,
      35.5,
      36.5,
      37.5,
      38.5,
      39.5,
      40.5,
      41.5,
      42.5,
      43.5,
      44.5,
      45.5,
      46.5,
      47.5,
      48.5,
      49.5,
      50.5,
      51.5
    ],
    "winners_density": [
      0.0,
      0.0,
      0.0,
      0.0,
      0.007518796992481203,
      0.0,
      0.007518796992481203,
      0.007518796992481203,
      0.0,
      0.0,
      0.007518796992481203,
      0.03759398496240601,
      0.015037593984962405,
      0.015037593984962405,
      0.03007518796992481,
      0.045112781954887216,
      0.06015037593984962,
      0.06015037593984962,
      0.08270676691729323,
      0.07518796992481203,
      0.03759398496240601,
      0.05263157894736842,
      0.06015037593984962,
      0.045112781954887216,
      0.06766917293233082,
      0.05263157894736842,
      0.05263157894736842,
      0.05263157894736842,
      0.022556390977443608,
      0.03007518796992481,
      0.03007518796992481,
      0.015037593984962405,
      0.022556390977443608,
      0.007518796992481203,
      0.0,
      0.0,
      0.0,
      0.0,
      0.0,
      0.0,
      0.0,
      0.0,
      0.0,
      0.0,
      0.0,
      0.0,
      0.0,
      0.0,
      0.0,
      0.0,
      0.0,
      0.0
    ],
    "non_winners_density": [
      0.0011176590123958545,
      0.001828896565738671,
      0.001625685836212152,
      0.003048160942897785,
      0.00406421459053038,
      0.0055882950619792725,
      0.005791505791505791,
      0.006705954074375127,
      0.008738061369640317,
      0.010363747205852468,
      0.01422475106685633,
      0.015037593984962405,
      0.01839057102214997,
      0.0203210729526519,
      0.02052428368217842,
      0.029567161146108516,
      0.03373298110140215,
      0.035053850843324526,
      0.041353383458646614,
      0.041353383458646614,
      0.041963015647226175,
      0.04714488925015241,
      0.047348099979678926,
      0.05171713066449909,
      0.05110749847591953,
      0.04724649461491567,
      0.04826254826254826,
      0.04460475513107092,
      0.03881324933956513,
      0.03881324933956513,
      0.03485064011379801,
      0.031192846982320666,
      0.027738264580369845,
      0.024893314366998577,
      0.021337126600284494,
      0.017171306644990857,
      0.013615118878276773,
      0.011989433042064622,
      0.010871774029668766,
      0.007417191627717944,
      0.005893111156269051,
      0.005385084332452754,
      0.0035561877667140826,
      0.002641739483844747,
      0.00203210729526519,
      0.001422475106685633,
      0.0007112375533428165,
      0.0005080268238162975,
      0.0007112375533428165,
      0.000203210729526519,
      0.000203210729526519,
      0.000203210729526519
    ],
    "winners_count": [
      0,
      0,
      0,
      0,
      1,
      0,
      1,
      1,
      0,
      0,
      1,
      5,
      2,
      2,
      4,
      6,
      8,
      8,
      11,
      10,
      5,
      7,
      8,
      6,
      9,
      7,
      7,
      7,
      3,
      4,
      4,
      2,
      3,
      1,
      0,
      0,
      0,
      0,
      0,
      0,
      0,
      0,
      0,
      0,
      0,
      0,
      0,
      0,
      0,
      0,
      0,
      0
    ],
    "non_winners_count": [
      11,
      18,
      16,
      30,
      40,
      55,
      57,
      66,
      86,
      102,
      140,
      148,
      181,
      200,
      202,
      291,
      332,
      345,
      407,
      407,
      413,
      464,
      466,
      509,
      503,
      465,
      475,
      439,
      382,
      382,
      343,
      307,
      273,
      245,
      210,
      169,
      134,
      118,
      107,
      73,
      58,
      53,
      35,
      26,
      20,
      14,
      7,
      5,
      7,
      2,
      2,
      2
    ],
    "winners_mean": 20.781954887218046,
    "non_winners_mean": 23.310404389351756
  }
}